{"name":"LpxLinks","tagline":"Gets the additional content download links for Logic Pro X","body":"# lpx_links\r\n\r\nlpx_links is a utilty to get the direct download links for the additional sample/sound content for Logic Pro X.\r\n\r\n\r\n  - It gets the most current links for version 10.2.0\r\n  - Creates a text file with all the links in them.\r\n  - Importing the links file into a download manager like the DownThemAll addon for FireFox should work well.\r\n\r\n> Please note that if you do not have version 10.2.0\r\n> installed the utility will most likely fail.\r\n\r\n\r\n### Version\r\n0.0.5 - final version\r\nThis is the final version of lpx_links and will hopefully be replaced by LogicLinks.\r\n\r\nLogicLinks will feature:\r\n* Download Manager\r\n* Content Installer (Install to User Defined Location)\r\n* Content Re-locator (Move content to another drive - with auto linking)\r\n* Content Re-linker (Attempts to fix broken)\r\n\r\n### Usage\r\n\r\nSimply open the terminal and paste the command below.\r\n\r\n```sh\r\n cd ~/Downloads; mkdir -p lpx_links/app ; cd lpx_links/app ; curl -#L https://github.com/davidteren/lpx_links/tarball/master | tar -xzv --strip-components 1 ; ./lpx_links.rb\r\n\r\n```\r\n\r\n### Development\r\n\r\nWant to contribute? Fork and let me know.\r\n\r\nLicense\r\n----\r\n\r\nGNU General Public License, version 3 (GPL-3.0)\r\n(http://opensource.org/licenses/GPL-3.0)\r\n","google":"","note":"Don't delete this file! It's used internally to help with page regeneration."}